MANIFEST.in
README.rst
setup.py
tutor_aliyun.egg-info/PKG-INFO
tutor_aliyun.egg-info/SOURCES.txt
tutor_aliyun.egg-info/dependency_links.txt
tutor_aliyun.egg-info/entry_points.txt
tutor_aliyun.egg-info/requires.txt
tutor_aliyun.egg-info/top_level.txt
tutoraliyun/__init__.py
tutoraliyun/plugin.py
tutoraliyun/patches/k8s-volumes
tutoraliyun/patches/kustomization
tutoraliyun/templates/aliyun/apps/aliyun-volumes-patch.yml
tutoraliyun/templates/aliyun/apps/elasticsearch-nas-volumes-patch.yml
tutoraliyun/templates/aliyun/apps/minio-nas-volumes-patch.yml
tutoraliyun/templates/aliyun/apps/mongodb-nas-volumes-patch.yml
tutoraliyun/templates/aliyun/apps/mysql-nas-volumes-patch.yml
tutoraliyun/templates/aliyun/apps/rabbitmq-nas-volumes-patch.yml