Metadata-Version: 1.2
Name: tutor-aliyun
Version: 0.0.8
Summary: Aliyun plugin for Tutor, for deploying edx instance to aliyun by tutor
Home-page: https://github.com/WeJie/tutor-aliyun
Author: weijie
Author-email: wejie00@foxmail.com
License: AGPLv3
Project-URL: Issue tracker, https://github.com/WeJie/tutor-aliyun/issues
Project-URL: Documentation, https://github.com/WeJie/tutor-aliyun
Project-URL: Community, https://github.com/WeJie/tutor-aliyun
Project-URL: Code, https://github.com/WeJie/tutor-aliyun
Platform: UNKNOWN
Classifier: Development Status :: 3 - Alpha
Classifier: Intended Audience :: Developers
Classifier: License :: OSI Approved :: GNU Affero General Public License v3
Classifier: Operating System :: OS Independent
Classifier: Programming Language :: Python
Classifier: Programming Language :: Python :: 3.5
Classifier: Programming Language :: Python :: 3.6
Classifier: Programming Language :: Python :: 3.7
Requires-Python: >=3.5
